deepteam/.DS_Store
deepteam/__init__.py
deepteam/_version.py
deepteam/attacks/__init__.py
deepteam/attacks/attack_simulator/__init__.py
deepteam/attacks/attack_simulator/attack_simulator.py
deepteam/attacks/attack_simulator/schema.py
deepteam/attacks/attack_simulator/utils.py
deepteam/attacks/base_attack.py
deepteam/attacks/multi_turn/__init__.py
deepteam/attacks/multi_turn/bad_likert_judge/__init__.py
deepteam/attacks/multi_turn/bad_likert_judge/bad_likert_judge.py
deepteam/attacks/multi_turn/bad_likert_judge/schema.py
deepteam/attacks/multi_turn/bad_likert_judge/template.py
deepteam/attacks/multi_turn/base_multi_turn_attack.py
deepteam/attacks/multi_turn/base_schema.py
deepteam/attacks/multi_turn/base_template.py
deepteam/attacks/multi_turn/constants.py
deepteam/attacks/multi_turn/crescendo_jailbreaking/__init__.py
deepteam/attacks/multi_turn/crescendo_jailbreaking/crescendo_jailbreaking.py
deepteam/attacks/multi_turn/crescendo_jailbreaking/schema.py
deepteam/attacks/multi_turn/crescendo_jailbreaking/template.py
deepteam/attacks/multi_turn/linear_jailbreaking/__init__.py
deepteam/attacks/multi_turn/linear_jailbreaking/linear_jailbreaking.py
deepteam/attacks/multi_turn/linear_jailbreaking/schema.py
deepteam/attacks/multi_turn/linear_jailbreaking/template.py
deepteam/attacks/multi_turn/sequential_break/__init__.py
deepteam/attacks/multi_turn/sequential_break/schema.py
deepteam/attacks/multi_turn/sequential_break/sequential_break.py
deepteam/attacks/multi_turn/sequential_break/template.py
deepteam/attacks/multi_turn/tree_jailbreaking/__init__.py
deepteam/attacks/multi_turn/tree_jailbreaking/schema.py
deepteam/attacks/multi_turn/tree_jailbreaking/template.py
deepteam/attacks/multi_turn/tree_jailbreaking/tree_jailbreaking.py
deepteam/attacks/multi_turn/types.py
deepteam/attacks/multi_turn/utils.py
deepteam/attacks/single_turn/__init__.py
deepteam/attacks/single_turn/adversarial_poetry/__init__.py
deepteam/attacks/single_turn/adversarial_poetry/adversarial_poetry.py
deepteam-1.0.5.dist-info/LICENSE.md
deepteam-1.0.5.dist-info/METADATA
deepteam-1.0.5.dist-info/WHEEL
deepteam-1.0.5.dist-info/entry_points.txt
deepteam-1.0.5.dist-info/RECORD
