Metadata-Version: 2.1
Name: deepteam
Version: 1.0.5
Summary: The LLM Red Teaming Framework
License: Apache-2.0
Author: Jeffrey Ip
Author-email: jeffreyip@confident-ai.com
Requires-Python: >=3.9,<3.14
Classifier: License :: OSI Approved :: Apache Software License
Classifier: Programming Language :: Python :: 3
Classifier: Programming Language :: Python :: 3.9
Classifier: Programming Language :: Python :: 3.10
Classifier: Programming Language :: Python :: 3.11
Requires-Dist: aiohttp (>=3.11.18)
Requires-Dist: deepeval (>=3.6.2)
Requires-Dist: grpcio (>=1.67.1)
Requires-Dist: openai (>=1.76.2)
Requires-Dist: pyyaml (>=6.0.2)
Requires-Dist: requests (>=2.31.0)
Requires-Dist: tabulate (>=0.9.0)
Requires-Dist: tqdm (>=4.66.1)
Project-URL: Documentation, https://trydeepteam.com
Project-URL: Issues, https://github.com/confident-ai/deepteam/issues
Project-URL: Repository, https://github.com/confident-ai/deepteam
